dwd4cast/__init__.py
dwd4cast/cli.py
dwd4cast-0.1.0.dist-info/METADATA
dwd4cast-0.1.0.dist-info/WHEEL
dwd4cast-0.1.0.dist-info/entry_points.txt
dwd4cast-0.1.0.dist-info/RECORD
