Metadata-Version: 2.1
Name: dwd4cast
Version: 0.1.0
Summary: python interface to collect and read GRIB files from the DWD
Home-page: https://github.com/stalbrec/dwd4cast
License: MIT
Author: Albrecht, Steffen
Author-email: steffen.alb@posteo.de
Requires-Python: >=3.9,<4.0
Classifier: Development Status :: 3 - Alpha
Classifier: Intended Audience :: Developers
Classifier: License :: OSI Approved :: MIT License
Classifier: Programming Language :: Python :: 3
Classifier: Programming Language :: Python :: 3.9
Classifier: Programming Language :: Python :: 3.10
Classifier: Programming Language :: Python :: 3.11
Classifier: Programming Language :: Python :: 3.12
Classifier: Programming Language :: Python :: 3 :: Only
Classifier: Topic :: Scientific/Engineering :: Atmospheric Science
Classifier: Topic :: Scientific/Engineering :: GIS
Classifier: Topic :: Software Development :: Libraries
Classifier: Topic :: Software Development :: Libraries :: Python Modules
Classifier: Topic :: Utilities
Requires-Dist: cfgrib (>=0.9.12,<0.10.0)
Requires-Dist: fastapi (>=0.111.0,<0.112.0)
Requires-Dist: numpy (>=1.26.4,<2.0.0)
Requires-Dist: requests (>=2.31.0,<3.0.0)
Requires-Dist: uvicorn (>=0.30.0,<0.31.0)
Requires-Dist: xarray (>=2024,<2025)
Project-URL: Repository, https://github.com/stalbrec/dwd4cast
